LICENSE
fonts/Arvo/Arvo-Bold.ttf
fonts/Arvo/Arvo-BoldItalic.ttf
fonts/Arvo/Arvo-Italic.ttf
fonts/Arvo/Arvo-Regular.ttf
fonts/Inconsolata/Inconsolata-Black.ttf
fonts/Inconsolata/Inconsolata-Bold.ttf
fonts/Inconsolata/Inconsolata-ExtraBold.ttf
fonts/Inconsolata/Inconsolata-ExtraLight.ttf
fonts/Inconsolata/Inconsolata-Light.ttf
fonts/Inconsolata/Inconsolata-Medium.ttf
fonts/Inconsolata/Inconsolata-Regular.ttf
fonts/Inconsolata/Inconsolata-SemiBold.ttf
fonts/Nunito_Sans/NunitoSans-Black.ttf
fonts/Nunito_Sans/NunitoSans-BlackItalic.ttf
fonts/Nunito_Sans/NunitoSans-Bold.ttf
fonts/Nunito_Sans/NunitoSans-BoldItalic.ttf
fonts/Nunito_Sans/NunitoSans-ExtraBold.ttf
fonts/Nunito_Sans/NunitoSans-ExtraBoldItalic.ttf
fonts/Nunito_Sans/NunitoSans-ExtraLight.ttf
fonts/Nunito_Sans/NunitoSans-ExtraLightItalic.ttf
fonts/Nunito_Sans/NunitoSans-Italic.ttf
fonts/Nunito_Sans/NunitoSans-Light.ttf
fonts/Nunito_Sans/NunitoSans-LightItalic.ttf
fonts/Nunito_Sans/NunitoSans-Regular.ttf
fonts/Nunito_Sans/NunitoSans-SemiBold.ttf
fonts/Nunito_Sans/NunitoSans-SemiBoldItalic.ttf
rootsstyle/__init__.py
rootsstyle/_colors.py
rootsstyle/_fonts.py
rootsstyle/_nnls.py
rootsstyle/_utils.py
rootsstyle/functions.py
rootsstyle/style.py
rootsstyle-0.5.1.dist-info/LICENSE
rootsstyle-0.5.1.dist-info/WHEEL
rootsstyle-0.5.1.dist-info/METADATA
rootsstyle-0.5.1.dist-info/RECORD
