Metadata-Version: 2.1
Name: rootsstyle
Version: 0.5.1
Summary: A dataroots inspired theme for matplotlib.
Home-page: https://github.com/yannouravoet
License: MIT
Author: YannouRavoet
Author-email: yannou.ravoet@dataroots.io
Requires-Python: >=3.8,<3.11
Classifier: License :: OSI Approved :: MIT License
Classifier: Programming Language :: Python :: 3
Classifier: Programming Language :: Python :: 3.10
Classifier: Programming Language :: Python :: 3.8
Classifier: Programming Language :: Python :: 3.9
Requires-Dist: matplotlib (>=3.5.0,<4.0.0)
